assemblyai_haystack/__init__.py
assemblyai_haystack/transcriber.py
assemblyai_haystack-0.1.1.dist-info/LICENSE
assemblyai_haystack-0.1.1.dist-info/METADATA
assemblyai_haystack-0.1.1.dist-info/WHEEL
assemblyai_haystack-0.1.1.dist-info/top_level.txt
assemblyai_haystack-0.1.1.dist-info/RECORD
