Metadata-Version: 2.1
Name: assemblyai-haystack
Version: 0.1.1
Summary: AssemblyAI Haystack Integration
Home-page: https://github.com/AssemblyAI/assemblyai-haystack
Author: AssemblyAI
Author-email: marketing@assemblyai.com
License: Apache License 2.0
Project-URL: Code, https://github.com/AssemblyAI/assemblyai-haystack
Project-URL: Issues, https://github.com/AssemblyAI/assemblyai-haystack/issues
Project-URL: Documentation, https://github.com/AssemblyAI/assemblyai-haystack/blob/main/README.md
Project-URL: API Documentation, https://www.assemblyai.com/docs/
Project-URL: Website, https://assemblyai.com/
Classifier: Development Status :: 3 - Alpha
Classifier: Intended Audience :: Developers
Classifier: Intended Audience :: Science/Research
Classifier: License :: OSI Approved :: Apache Software License
Classifier: Natural Language :: English
Classifier: Topic :: Scientific/Engineering :: Artificial Intelligence
Classifier: Topic :: Software Development :: Libraries
Classifier: Topic :: Software Development :: Libraries :: Python Modules
Classifier: Programming Language :: Python :: 3
Classifier: Programming Language :: Python :: 3.8
Classifier: Programming Language :: Python :: 3.9
Classifier: Programming Language :: Python :: 3.10
Classifier: Programming Language :: Python :: 3.11
Requires-Python: >=3.8
License-File: LICENSE
Requires-Dist: haystack-ai
Requires-Dist: assemblyai >=0.18.0
